DataSciBuddy/__init__.py
DataSciBuddy/helper_functions.py
DataSciBuddy/datasets/fraud_data.csv
DataSciBuddy/datasets/house_prices.csv
DataSciBuddy-0.2.dist-info/LICENSE
DataSciBuddy-0.2.dist-info/METADATA
DataSciBuddy-0.2.dist-info/WHEEL
DataSciBuddy-0.2.dist-info/top_level.txt
DataSciBuddy-0.2.dist-info/RECORD
