Metadata-Version: 2.1
Name: DataSciBuddy
Version: 0.2
Summary: A data science helper package with datasets and utilities.
Home-page: https://github.com/nicholaskarlson/DataSciBuddy
Author: Nicholas Karlson
Author-email: NicholasKarlson@gmail.com
Classifier: Programming Language :: Python :: 3
Classifier: License :: OSI Approved :: MIT License
Classifier: Operating System :: OS Independent
Requires-Python: >=3.6
License-File: LICENSE
Requires-Dist: numpy
Requires-Dist: pandas
